{"type":"FeatureCollection","features":[{"type":"Feature","id":"poteau_electrique_geo.1","geometry":{"type":"Point","coordinates":[-3.96706304,5.35445322]},"geometry_name":"geom","properties":{"id_poteau":"POT000000001","typ_pt":null,"nature_pt":null,"mode_utils":null,"assemblage":null,"type_isola":null,"descriptio":null,"id_parent":null,"code_poste":null}},{"type":"Feature","id":"poteau_electrique_geo.2","geometry":{"type":"Point","coordinates":[-3.96707434,5.35404212]},"geometry_name":"geom","properties":{"id_poteau":"POT000000002","typ_pt":null,"nature_pt":null,"mode_utils":null,"assemblage":null,"type_isola":null,"descriptio":null,"id_parent":null,"code_poste":null}},{"type":"Feature","id":"poteau_electrique_geo.3","geometry":{"type":"Point","coordinates":[-3.96709721,5.35339551]},"geometry_name":"geom","properties":{"id_poteau":"POT000000003","typ_pt":null,"nature_pt":null,"mode_utils":null,"assemblage":null,"type_isola":null,"descriptio":null,"id_parent":null,"code_poste":null}},{"type":"Feature","id":"poteau_electrique_geo.4","geometry":{"type":"Point","coordinates":[-3.96641626,5.35338062]},"geometry_name":"geom","properties":{"id_poteau":"POT000000004","typ_pt":null,"nature_pt":null,"mode_utils":null,"assemblage":null,"type_isola":null,"descriptio":null,"id_parent":null,"code_poste":null}},{"type":"Feature","id":"poteau_electrique_geo.5","geometry":{"type":"Point","coordinates":[-3.96526134,5.35330661]},"geometry_name":"geom","properties":{"id_poteau":"POT000000005","typ_pt":null,"nature_pt":null,"mode_utils":null,"assemblage":null,"type_isola":null,"descriptio":null,"id_parent":null,"code_poste":null}},{"type":"Feature","id":"poteau_electrique_geo.6","geometry":{"type":"Point","coordinates":[-3.96527265,5.35289949]},"geometry_name":"geom","properties":{"id_poteau":"POT000000006","typ_pt":null,"nature_pt":null,"mode_utils":null,"assemblage":null,"type_isola":null,"descriptio":null,"id_parent":null,"code_poste":null}},{"type":"Feature","id":"poteau_electrique_geo.7","geometry":{"type":"Point","coordinates":[-3.96525236,5.35265606]},"geometry_name":"geom","properties":{"id_poteau":"POT000000007","typ_pt":null,"nature_pt":null,"mode_utils":null,"assemblage":null,"type_isola":null,"descriptio":null,"id_parent":null,"code_poste":null}}],"totalFeatures":7,"numberMatched":7,"numberReturned":7,"timeStamp":"2023-01-22T18:07:06.269Z","crs":{"type":"name","properties":{"name":"urn:ogc:def:crs:EPSG::4326"}}}